{
  "$schema": "../schemas/design-system.schema.json5",
  "name": "Spectrum",
  "description": "Spectrum provides components and tools to help product teams work more efficiently, and to make Adobe’s applications more cohesive.",
  "url": "http://spectrum.adobe.com",
  "by": "Adobe",
  "components": [
    {
      "name": "Menu",
      "url": "https://react-spectrum.adobe.com/react-spectrum/Menu.html",
      "concepts": [
        {
          "name": "basic",
          "image": "spectrum-menu-basic.png"
        },
        {
          "name": "section",
          "image": "spectrum-menu-section.png"
        },
        {
          "name": "selection",
          "image": "spectrum-menu-selection.png"
        }
      ]
    }
  ]
}
